.DS_Store
rarity/.DS_Store
rarity/__init__.py
rarity/analyzer.py
rarity/app.py
rarity/py.typed
rarity/assets/01_bootstrap.min.css
rarity/assets/02_styles.css
rarity/assets/MAE.png
rarity/assets/MSE.png
rarity/assets/R2.png
rarity/assets/RMSE.png
rarity/assets/bootstrap.min.css
rarity/assets/favicon.ico
rarity/assets/rarity-icon.png
rarity/assets/styles.css
rarity/data_loader/__init__.py
rarity/data_loader/base_loader.py
rarity/data_loader/data_loader.py
rarity/features/__init__.py
rarity/features/feat_feature_distribution.py
rarity/features/feat_general_metrics.py
rarity/features/feat_loss_clusters.py
rarity/features/feat_miss_predictions.py
rarity/features/feat_similarities_counter_factuals.py
rarity/interpreters/__init__.py
rarity/interpreters/structured_data/__init__.py
rarity/interpreters/structured_data/base_interpreters.py
rarity/interpreters/structured_data/int_general_metrics.py
rarity/interpreters/structured_data/int_loss_clusters.py
rarity/interpreters/structured_data/int_miss_predictions.py
rarity/interpreters/structured_data/int_similarities_counter_factuals.py
rarity/interpreters/structured_data/int_xfeature_distribution.py
rarity/utils/__init__.py
rarity/utils/common_functions.py
rarity/utils/methods.py
rarity/utils/style_configs.py
rarity/visualizers/__init__.py
rarity/visualizers/general_metrics.py
rarity/visualizers/loss_clusters.py
rarity/visualizers/miss_predictions.py
rarity/visualizers/shared_viz_component.py
rarity/visualizers/xfeature_distribution.py
rarity-1.0.2.dist-info/LICENSE
rarity-1.0.2.dist-info/METADATA
rarity-1.0.2.dist-info/WHEEL
rarity-1.0.2.dist-info/entry_points.txt
rarity-1.0.2.dist-info/top_level.txt
rarity-1.0.2.dist-info/RECORD
