Metadata-Version: 2.1
Name: rarity
Version: 1.0.2
Summary: Data diagnostic package with minimum setup to analyze miss predictions of ML models
Home-page: https://github.com/aimakerspace/Rarity
Author: Yap Siew Lin @ AI Singapore, Jeanne Choo (ex-AISG), Chong Wei Yih (ex-AISG)
Author-email: siewlin@aisingapore.org
License: Apache 2.0
Keywords: data analysis model prediction diagnostic
Platform: UNKNOWN
Classifier: Development Status :: 4 - Beta
Classifier: Intended Audience :: Developers
Classifier: Intended Audience :: Education
Classifier: Intended Audience :: Science/Research
Classifier: License :: OSI Approved :: Apache Software License
Classifier: Operating System :: OS Independent
Classifier: Programming Language :: Python :: 3.6
Classifier: Programming Language :: Python :: 3.7
Classifier: Programming Language :: Python :: 3.8
Classifier: Topic :: Scientific/Engineering :: Artificial Intelligence
Requires-Python: >=3.6.0
Requires-Dist: pandas (>=1.2.4)
Requires-Dist: scikit-learn (>=0.24.1)
Requires-Dist: statsmodels (==0.12.2)
Requires-Dist: plotly (>=4.14.3)
Requires-Dist: dash (==1.20.0)
Requires-Dist: dash-bootstrap-components (==0.12.2)
Requires-Dist: dash-core-components (==1.16.0)
Requires-Dist: dash-html-components (==1.1.3)
Provides-Extra: docs
Requires-Dist: Sphinx (>=3.0.0) ; extra == 'docs'
Requires-Dist: sphinx-rtd-theme (==0.5.2) ; extra == 'docs'
Requires-Dist: docutils (==0.16) ; extra == 'docs'
Requires-Dist: sphinxcontrib-serializinghtml (==1.1.5) ; extra == 'docs'
Requires-Dist: pylons-sphinx-themes (>=1.0.8) ; extra == 'docs'
Requires-Dist: pylons-sphinx-latesturl ; extra == 'docs'
Requires-Dist: repoze.sphinx.autointerface ; extra == 'docs'
Requires-Dist: sphinxcontrib-autoprogram ; extra == 'docs'
Provides-Extra: notebook
Requires-Dist: jupyter-client (>=6.0.0) ; extra == 'notebook'
Requires-Dist: jupyter-core (>=4.6.3) ; extra == 'notebook'
Requires-Dist: ipywidgets (>=7.5.1) ; extra == 'notebook'
